mistifi/__init__.py
mistifi/_version.py
mistifi/mistifi.py
mistifi/tests/__init__.py
mistifi/tests/test_mist.py
mistifi/tests/test_data/__init__.py
mistifi/tests/test_data/test_data.py
mistifi-0.0.9.dist-info/LICENSE.md
mistifi-0.0.9.dist-info/METADATA
mistifi-0.0.9.dist-info/WHEEL
mistifi-0.0.9.dist-info/top_level.txt
mistifi-0.0.9.dist-info/RECORD
