Metadata-Version: 2.1
Name: mistifi
Version: 0.0.9
Summary: Mist API Python module
Home-page: UNKNOWN
Author: Primoz Marinsek
Author-email: primoz.marinsek@ocado.com
License: Apache-2.0
Platform: UNKNOWN
Requires-Dist: requests
Requires-Dist: logzero
